SalmonEuAdmix/__init__.py
SalmonEuAdmix/cli.py
SalmonEuAdmix/encode.py
SalmonEuAdmix/model.py
SalmonEuAdmix/data/SNP_impute_info.pkl
SalmonEuAdmix/data/SNP_major_minor_info.pkl
SalmonEuAdmix/data/X_scaler_v1
SalmonEuAdmix/data/X_scaler_v4
SalmonEuAdmix/data/dnn_301_tf.h5
SalmonEuAdmix/data/dnn_513_tf.h5
SalmonEuAdmix/data/panel_301_data.map
SalmonEuAdmix/data/panel_301_data.ped
SalmonEuAdmix/data/panel_513_data.map
SalmonEuAdmix/data/panel_513_data.ped
SalmonEuAdmix/data/reduced_marker_list.pkl
SalmonEuAdmix/data/unit_test2.map
SalmonEuAdmix/data/unit_test2.ped
SalmonEuAdmix/data/unit_test3.map
SalmonEuAdmix/data/unit_test3.ped
SalmonEuAdmix/data/y_scaler_v1
SalmonEuAdmix/data/y_scaler_v4
SalmonEuAdmix-1.0.6.dist-info/LICENCE.md
SalmonEuAdmix-1.0.6.dist-info/METADATA
SalmonEuAdmix-1.0.6.dist-info/WHEEL
SalmonEuAdmix-1.0.6.dist-info/entry_points.txt
SalmonEuAdmix-1.0.6.dist-info/top_level.txt
SalmonEuAdmix-1.0.6.dist-info/RECORD
