Metadata-Version: 2.1
Name: SalmonEuAdmix
Version: 1.0.6
Summary: Estimating European admixture proportions in Atlantic salmon
Home-page: https://github.com/CNuge/SalmonEuAdmix
Author: Cam Nugent
Author-email: Cameron.Nugent@dfo-mpo.gc.ca
License: LICENSE.md
Requires-Python: >=3.9.7
License-File: LICENCE.md
Requires-Dist: numpy (>=1.20.3)
Requires-Dist: pandas (>=1.3.4)
Requires-Dist: tensorflow (>=2.8.0)
Requires-Dist: scikit-learn (>=0.24.2)
Requires-Dist: pytest (==6.2.4)
